aws_nova_canvas_mcp/__init__.py
aws_nova_canvas_mcp/config.py
aws_nova_canvas_mcp/exceptions.py
aws_nova_canvas_mcp/server.py
aws_nova_canvas_mcp/tools/__init__.py
aws_nova_canvas_mcp/tools/background_removal.py
aws_nova_canvas_mcp/tools/color_guided_generation.py
aws_nova_canvas_mcp/tools/image_conditioning.py
aws_nova_canvas_mcp/tools/image_variation.py
aws_nova_canvas_mcp/tools/inpainting.py
aws_nova_canvas_mcp/tools/outpainting.py
aws_nova_canvas_mcp/tools/text_to_image.py
aws_nova_canvas_mcp/utils/__init__.py
aws_nova_canvas_mcp/utils/bedrock.py
aws_nova_canvas_mcp/utils/image.py
aws_nova_canvas_mcp/utils/image_storage.py
aws_nova_canvas_mcp-0.1.6.dist-info/licenses/LICENSE
aws_nova_canvas_mcp-0.1.6.dist-info/METADATA
aws_nova_canvas_mcp-0.1.6.dist-info/WHEEL
aws_nova_canvas_mcp-0.1.6.dist-info/entry_points.txt
aws_nova_canvas_mcp-0.1.6.dist-info/top_level.txt
aws_nova_canvas_mcp-0.1.6.dist-info/RECORD
