Metadata-Version: 2.4
Name: aws-nova-canvas-mcp
Version: 0.1.6
Summary: An MCP server that allows you to generate and edit images using the Nova Canvas model of Amazon Bedrock
Requires-Python: >=3.12
License-File: LICENSE
Requires-Dist: boto3>=1.37.23
Requires-Dist: mcp[cli]>=1.6.0
Requires-Dist: python-dotenv>=1.1.0
Requires-Dist: requests>=2.32.3
Dynamic: license-file
